{
  "main": {
    "id": "b47ee2905655d5d5",
    "type": "split",
    "children": [
      {
        "id": "7e94b99d61b15853",
        "type": "tabs",
        "children": [
          {
            "id": "9d74a1ae269fdc5a",
            "type": "leaf",
            "state": {
              "type": "empty",
              "state": {}
            }
          }
        ]
      }
    ],
    "direction": "vertical"
  },
  "left": {
    "id": "587f03f64c49e397",
    "type": "split",
    "children": [
      {
        "id": "0df691d8a8e55ff5",
        "type": "tabs",
        "children": [
          {
            "id": "ce05c4fbe975b0ff",
            "type": "leaf",
            "state": {
              "type": "file-explorer",
              "state": {
                "sortOrder": "alphabetical"
              }
            }
          },
          {
            "id": "205dddaf951a670f",
            "type": "leaf",
            "state": {
              "type": "search",
              "state": {
                "query": "",
                "matchingCase": false,
                "explainSearch": false,
                "collapseAll": false,
                "extraContext": false,
                "sortOrder": "alphabetical"
              }
            }
          },
          {
            "id": "4eaf40046d004ad8",
            "type": "leaf",
            "state": {
              "type": "bookmarks",
              "state": {}
            }
          }
        ]
      }
    ],
    "direction": "horizontal",
    "width": 300
  },
  "right": {
    "id": "0943490ab3f22e17",
    "type": "split",
    "children": [
      {
        "id": "2e9d119459277b04",
        "type": "tabs",
        "children": [
          {
            "id": "c877442d3c2d8f13",
            "type": "leaf",
            "state": {
              "type": "backlink",
              "state": {
                "file": "website/blog/2023-06-01/Post1.md",
                "collapseAll": false,
                "extraContext": false,
                "sortOrder": "alphabetical",
                "showSearch": false,
                "searchQuery": "",
                "backlinkCollapsed": false,
                "unlinkedCollapsed": true
              }
            }
          },
          {
            "id": "563fe2c0c19a5bc0",
            "type": "leaf",
            "state": {
              "type": "outgoing-link",
              "state": {
                "file": "website/blog/2023-06-01/Post1.md",
                "linksCollapsed": false,
                "unlinkedCollapsed": true
              }
            }
          },
          {
            "id": "8eb775374d092862",
            "type": "leaf",
            "state": {
              "type": "tag",
              "state": {
                "sortOrder": "frequency",
                "useHierarchy": true
              }
            }
          },
          {
            "id": "64b1e7fc9dd093bf",
            "type": "leaf",
            "state": {
              "type": "outline",
              "state": {
                "file": "website/blog/2023-06-01/Post1.md"
              }
            }
          }
        ]
      }
    ],
    "direction": "horizontal",
    "width": 300,
    "collapsed": true
  },
  "left-ribbon": {
    "hiddenItems": {
      "switcher:퀵 스위처 열기": false,
      "graph:그래프 뷰 열기": false,
      "canvas:새 캔버스 만들기": false,
      "daily-notes:오늘의 데일리 노트 열기": false,
      "templates:템플릿 삽입": false,
      "command-palette:명령어 팔레트 열기": false,
      "obsidiosaurus:Obsidiosaurus": false
    }
  },
  "active": "ce05c4fbe975b0ff",
  "lastOpenFiles": [
    "vault/blog/2023-06-01/Post1__en.md",
    "website/blog/yoonu/ms.md",
    "website/blog/yoonu/kaymak.md",
    "vault/blog/yoonu/ms.md",
    "vault/blog/yoonu/kaymak.md",
    "website/blog/yoonu/2023-09-15-test.md",
    "vault/blog/yoonu/2023-09-15-test.md",
    "conflict-files-obsidian-git.md",
    "vault/blog/first test1.md",
    "vault/blog/yoonu/2023-09-16-test 2.md",
    "vault/blog/yoonu/2023-09-16-test 1.md"
  ]
}